notipy_osx/__init__.py
notipy_osx/_dialog.py
notipy_osx/_result.py
notipy_osx/_testing.py
notipy_osx/choice.py
notipy_osx/dialog.py
notipy_osx/notification.py
notipy_osx/result.py
notipy_osx/testing.py
notipy_osx-0.0.9.dist-info/LICENSE
notipy_osx-0.0.9.dist-info/METADATA
notipy_osx-0.0.9.dist-info/WHEEL
notipy_osx-0.0.9.dist-info/top_level.txt
notipy_osx-0.0.9.dist-info/RECORD
