Metadata-Version: 2.1
Name: notipy-osx
Version: 0.0.9
Summary: Deprecated, use aquaui instead
Home-page: https://notipy.now.sh/
License: MIT
Project-URL: Bug Tracker, https://github.com/ninest/aquaui/issues
Project-URL: Documentation, https://github.com/ninest/aquaui
Project-URL: Source Code, https://github.com/ninest/aquaui
Platform: UNKNOWN
Requires-Python: >=3.6
